pydsmc/__init__.py
pydsmc/evaluator.py
pydsmc/json_parser.py
pydsmc/property.py
pydsmc/py.typed
pydsmc/statistics.py
pydsmc/utils.py
pydsmc-0.3.2.dist-info/METADATA
pydsmc-0.3.2.dist-info/WHEEL
pydsmc-0.3.2.dist-info/licenses/LICENSE
pydsmc-0.3.2.dist-info/RECORD
