Metadata-Version: 2.4
Name: pydsmc
Version: 0.3.2
Summary: Statistical Model Checking for Neural Agents Using the Gymnasium Interface
License-Expression: MIT
License-File: LICENSE
Author: Timo P. Gros
Author-email: timopgros@cs.uni-saarland.de
Maintainer: Joshua Meyer
Maintainer-email: joshua.meyer@cs.uni-saarland.de
Requires-Python: >= 3.9
Classifier: Programming Language :: Python :: 3
Classifier: Programming Language :: Python :: 3.9
Classifier: Programming Language :: Python :: 3.10
Classifier: Programming Language :: Python :: 3.11
Classifier: Programming Language :: Python :: 3.12
Classifier: Programming Language :: Python :: 3.13
Classifier: Programming Language :: Python :: 3.14
Requires-Dist: gymnasium (>=0.28.1,<2.0.0)
Requires-Dist: numpy (>=1.26.4,<3.0.0)
Requires-Dist: packaging (>=20.0)
Requires-Dist: scipy (>=1.13.1,<2.0.0)
Project-URL: Issues, https://github.com/neuro-mechanistic-modeling/PyDSMC/issues
Project-URL: Repository, https://github.com/neuro-mechanistic-modeling/pydsmc
